chainfix/__init__.py
chainfix/binary.py
chainfix/context.py
chainfix/decimal.py
chainfix/fixed_point.py
chainfix/helpers.py
chainfix-0.1.2.dist-info/licenses/LICENSE
chainfix-0.1.2.dist-info/METADATA
chainfix-0.1.2.dist-info/WHEEL
chainfix-0.1.2.dist-info/top_level.txt
chainfix-0.1.2.dist-info/RECORD
