Metadata-Version: 2.4
Name: chainfix
Version: 0.1.2
Summary: Fixed-point data types for signal processing and blockchain applications
Author-email: PyDefi Development Team <MikesRND@users.noreply.github.com>
License:                                  Apache License
Project-URL: Homepage, https://github.com/pydefi/chainfix
Project-URL: Repository, https://github.com/pydefi/chainfix
Project-URL: Issues, https://github.com/pydefi/chainfix/issues
Keywords: fixed-point,binary fixed-point,decimal fixed-point
Classifier: Development Status :: 3 - Alpha
Classifier: Intended Audience :: Developers
Classifier: License :: OSI Approved :: Apache Software License
Classifier: Topic :: Scientific/Engineering :: Mathematics
Classifier: Topic :: Office/Business :: Financial
Classifier: Topic :: Scientific/Engineering :: Electronic Design Automation (EDA)
Classifier: Programming Language :: Python :: 3
Classifier: Programming Language :: Python :: 3.8
Classifier: Programming Language :: Python :: 3.9
Classifier: Programming Language :: Python :: 3.10
Classifier: Programming Language :: Python :: 3.11
Classifier: Programming Language :: Python :: 3.12
Classifier: Programming Language :: Python :: 3.13
Requires-Python: >=3.8
License-File: LICENSE
Dynamic: license-file
